LICENSE
MANIFEST.in
README.rst
requirements.txt
setup.cfg
setup.py
versioneer.py
cfgset/__init__.py
cfgset/_version.py
cfgset/cfgset.py
cfgset.egg-info/PKG-INFO
cfgset.egg-info/SOURCES.txt
cfgset.egg-info/dependency_links.txt
cfgset.egg-info/entry_points.txt
cfgset.egg-info/not-zip-safe
cfgset.egg-info/requires.txt
cfgset.egg-info/top_level.txt