Metadata-Version: 1.1
Name: cfgset
Version: 0.1
Summary: Query interface to prioritised collections of CfgStacks
Home-page: https://github.com/clearclaw/cfgset
Author: J C Lawrence
Author-email: claw@kanga.nu
License: LGPL v3.0
Keywords: config sets,configfile,file stacks,reference trees
Platform: UNKNOWN
Classifier: Development Status :: 4 - Beta
Classifier: Intended Audience :: Developers
Classifier: License :: OSI Approved :: GNU Lesser General Public License v3 or later (LGPLv3+)
Classifier: Topic :: Utilities
